{
    "image": "generated.photos_v3_0354313.jpg",
    "faceLandmarks": {
        "mouth": [
            {
                "x": 392,
                "y": 728
            },
            {
                "x": 440,
                "y": 704
            },
            {
                "x": 488,
                "y": 696
            },
            {
                "x": 520,
                "y": 696
            },
            {
                "x": 552,
                "y": 696
            },
            {
                "x": 584,
                "y": 704
            },
            {
                "x": 624,
                "y": 728
            },
            {
                "x": 592,
                "y": 776
            },
            {
                "x": 552,
                "y": 800
            },
            {
                "x": 520,
                "y": 800
            },
            {
                "x": 488,
                "y": 800
            },
            {
                "x": 440,
                "y": 776
            },
            {
                "x": 408,
                "y": 728
            },
            {
                "x": 488,
                "y": 720
            },
            {
                "x": 520,
                "y": 720
            },
            {
                "x": 552,
                "y": 720
            },
            {
                "x": 608,
                "y": 728
            },
            {
                "x": 552,
                "y": 752
            },
            {
                "x": 520,
                "y": 760
            },
            {
                "x": 488,
                "y": 760
            }
        ],
        "right_eyebrow": [
            {
                "x": 280,
                "y": 432
            },
            {
                "x": 320,
                "y": 400
            },
            {
                "x": 368,
                "y": 384
            },
            {
                "x": 424,
                "y": 392
            },
            {
                "x": 472,
                "y": 416
            }
        ],
        "left_eyebrow": [
            {
                "x": 560,
                "y": 416
            },
            {
                "x": 600,
                "y": 400
            },
            {
                "x": 648,
                "y": 392
            },
            {
                "x": 696,
                "y": 400
            },
            {
                "x": 728,
                "y": 440
            }
        ],
        "right_eye": [
            {
                "x": 344,
                "y": 480
            },
            {
                "x": 376,
                "y": 472
            },
            {
                "x": 408,
                "y": 472
            },
            {
                "x": 432,
                "y": 496
            },
            {
                "x": 400,
                "y": 496
            },
            {
                "x": 368,
                "y": 496
            }
        ],
        "left_eye": [
            {
                "x": 584,
                "y": 496
            },
            {
                "x": 608,
                "y": 472
            },
            {
                "x": 640,
                "y": 472
            },
            {
                "x": 672,
                "y": 488
            },
            {
                "x": 648,
                "y": 496
            },
            {
                "x": 616,
                "y": 496
            }
        ],
        "nose": [
            {
                "x": 512,
                "y": 472
            },
            {
                "x": 520,
                "y": 520
            },
            {
                "x": 520,
                "y": 568
            },
            {
                "x": 520,
                "y": 616
            },
            {
                "x": 456,
                "y": 648
            },
            {
                "x": 488,
                "y": 656
            },
            {
                "x": 520,
                "y": 656
            },
            {
                "x": 552,
                "y": 656
            }
        ],
        "jaw": [
            {
                "x": 200,
                "y": 488
            },
            {
                "x": 208,
                "y": 560
            },
            {
                "x": 224,
                "y": 632
            },
            {
                "x": 240,
                "y": 704
            },
            {
                "x": 272,
                "y": 768
            },
            {
                "x": 312,
                "y": 824
            },
            {
                "x": 376,
                "y": 872
            },
            {
                "x": 440,
                "y": 904
            },
            {
                "x": 512,
                "y": 920
            },
            {
                "x": 584,
                "y": 904
            },
            {
                "x": 640,
                "y": 864
            },
            {
                "x": 688,
                "y": 816
            },
            {
                "x": 728,
                "y": 752
            },
            {
                "x": 744,
                "y": 688
            },
            {
                "x": 752,
                "y": 624
            },
            {
                "x": 760,
                "y": 552
            },
            {
                "x": 760,
                "y": 488
            }
        ]
    },
    "faceAttributes": {
        "headPose": {
            "pitch": 0.17,
            "roll": 0.11,
            "yaw": 4.11
        },
        "gender": {
            "male": 0.07,
            "female": 0.93
        },
        "makeup": {
            "eyeMakeup": 0.83,
            "lipMakeup": 0.72
        },
        "emotion": {
            "anger": 0.0,
            "contempt": 0.02,
            "disgust": 0.02,
            "fear": 0.0,
            "happiness": 0.81,
            "neutral": 0.08,
            "sadness": 0.03,
            "surprise": 0.02
        },
        "facialHair": {
            "moustache": -0.02,
            "beard": -0.02,
            "sideburns": -0.02
        },
        "hair": {
            "hairColor": [
                {
                    "name": "brown",
                    "confidence": 0.91
                },
                {
                    "name": "black",
                    "confidence": 0.85
                },
                {
                    "name": "blond",
                    "confidence": 0.13
                },
                {
                    "name": "red",
                    "confidence": 0.16
                },
                {
                    "name": "gray",
                    "confidence": 0.26
                },
                {
                    "name": "other",
                    "confidence": 0.23
                }
            ],
            "hairLength": [
                {
                    "name": "Long",
                    "confidence": 0.62
                },
                {
                    "name": "Medium",
                    "confidence": 0.37
                },
                {
                    "name": "Short",
                    "confidence": 0.0
                }
            ],
            "bald": 0.11
        },
        "occlusion": {
            "foreheadOccluded": -0.01,
            "eyeOccluded": 0.0,
            "mouthOccluded": 0.0
        },
        "ethnicity": [
            {
                "name": "asian",
                "confidence": 0.35
            },
            {
                "name": "black",
                "confidence": 0.01
            },
            {
                "name": "latino",
                "confidence": 0.59
            },
            {
                "name": "white",
                "confidence": 0.05
            }
        ],
        "eye_color": [
            {
                "name": "Blue",
                "confidence": 0.03
            },
            {
                "name": "Brown",
                "confidence": 0.92
            },
            {
                "name": "Green",
                "confidence": 0.01
            },
            {
                "name": "Grey",
                "confidence": 0.04
            }
        ],
        "smile": 0.81,
        "age": 27.24
    },
    "bug_probability": 0.0
}