{
    "image": "generated.photos_v3_0512928.jpg",
    "faceLandmarks": {
        "mouth": [
            {
                "x": 400,
                "y": 728
            },
            {
                "x": 440,
                "y": 712
            },
            {
                "x": 472,
                "y": 704
            },
            {
                "x": 504,
                "y": 712
            },
            {
                "x": 536,
                "y": 704
            },
            {
                "x": 576,
                "y": 712
            },
            {
                "x": 616,
                "y": 728
            },
            {
                "x": 576,
                "y": 768
            },
            {
                "x": 536,
                "y": 784
            },
            {
                "x": 504,
                "y": 784
            },
            {
                "x": 472,
                "y": 784
            },
            {
                "x": 440,
                "y": 768
            },
            {
                "x": 424,
                "y": 736
            },
            {
                "x": 472,
                "y": 736
            },
            {
                "x": 504,
                "y": 736
            },
            {
                "x": 536,
                "y": 736
            },
            {
                "x": 600,
                "y": 736
            },
            {
                "x": 536,
                "y": 744
            },
            {
                "x": 504,
                "y": 744
            },
            {
                "x": 472,
                "y": 744
            }
        ],
        "right_eyebrow": [
            {
                "x": 272,
                "y": 424
            },
            {
                "x": 312,
                "y": 392
            },
            {
                "x": 360,
                "y": 384
            },
            {
                "x": 408,
                "y": 392
            },
            {
                "x": 456,
                "y": 416
            }
        ],
        "left_eyebrow": [
            {
                "x": 552,
                "y": 408
            },
            {
                "x": 600,
                "y": 392
            },
            {
                "x": 648,
                "y": 384
            },
            {
                "x": 696,
                "y": 392
            },
            {
                "x": 744,
                "y": 416
            }
        ],
        "right_eye": [
            {
                "x": 336,
                "y": 480
            },
            {
                "x": 368,
                "y": 464
            },
            {
                "x": 400,
                "y": 464
            },
            {
                "x": 440,
                "y": 496
            },
            {
                "x": 400,
                "y": 504
            },
            {
                "x": 360,
                "y": 504
            }
        ],
        "left_eye": [
            {
                "x": 576,
                "y": 496
            },
            {
                "x": 608,
                "y": 464
            },
            {
                "x": 648,
                "y": 464
            },
            {
                "x": 680,
                "y": 480
            },
            {
                "x": 656,
                "y": 504
            },
            {
                "x": 616,
                "y": 504
            }
        ],
        "nose": [
            {
                "x": 504,
                "y": 472
            },
            {
                "x": 504,
                "y": 520
            },
            {
                "x": 504,
                "y": 568
            },
            {
                "x": 504,
                "y": 624
            },
            {
                "x": 456,
                "y": 648
            },
            {
                "x": 480,
                "y": 656
            },
            {
                "x": 504,
                "y": 672
            },
            {
                "x": 528,
                "y": 656
            }
        ],
        "jaw": [
            {
                "x": 232,
                "y": 456
            },
            {
                "x": 240,
                "y": 528
            },
            {
                "x": 256,
                "y": 600
            },
            {
                "x": 264,
                "y": 672
            },
            {
                "x": 288,
                "y": 736
            },
            {
                "x": 328,
                "y": 800
            },
            {
                "x": 376,
                "y": 848
            },
            {
                "x": 440,
                "y": 896
            },
            {
                "x": 504,
                "y": 904
            },
            {
                "x": 576,
                "y": 896
            },
            {
                "x": 640,
                "y": 856
            },
            {
                "x": 696,
                "y": 808
            },
            {
                "x": 736,
                "y": 752
            },
            {
                "x": 760,
                "y": 688
            },
            {
                "x": 768,
                "y": 616
            },
            {
                "x": 784,
                "y": 544
            },
            {
                "x": 792,
                "y": 464
            }
        ]
    },
    "faceAttributes": {
        "headPose": {
            "pitch": -4.24,
            "roll": 0.23,
            "yaw": -1.83
        },
        "gender": {
            "male": 0.19,
            "female": 0.81
        },
        "makeup": {
            "eyeMakeup": 0.75,
            "lipMakeup": 0.59
        },
        "emotion": {
            "anger": 0.01,
            "contempt": 0.03,
            "disgust": 0.03,
            "fear": -0.0,
            "happiness": 0.6,
            "neutral": 0.28,
            "sadness": 0.04,
            "surprise": 0.01
        },
        "facialHair": {
            "moustache": 0.01,
            "beard": 0.01,
            "sideburns": 0.01
        },
        "hair": {
            "hairColor": [
                {
                    "name": "brown",
                    "confidence": 0.92
                },
                {
                    "name": "black",
                    "confidence": 0.69
                },
                {
                    "name": "blond",
                    "confidence": 0.31
                },
                {
                    "name": "red",
                    "confidence": 0.22
                },
                {
                    "name": "gray",
                    "confidence": 0.27
                },
                {
                    "name": "other",
                    "confidence": 0.18
                }
            ],
            "hairLength": [
                {
                    "name": "Long",
                    "confidence": 0.05
                },
                {
                    "name": "Medium",
                    "confidence": 0.8
                },
                {
                    "name": "Short",
                    "confidence": 0.07
                }
            ],
            "bald": 0.17
        },
        "occlusion": {
            "foreheadOccluded": 0.0,
            "eyeOccluded": 0.0,
            "mouthOccluded": 0.0
        },
        "ethnicity": [
            {
                "name": "asian",
                "confidence": 0.16
            },
            {
                "name": "black",
                "confidence": 0.02
            },
            {
                "name": "latino",
                "confidence": 0.57
            },
            {
                "name": "white",
                "confidence": 0.26
            }
        ],
        "eye_color": [
            {
                "name": "Blue",
                "confidence": 0.02
            },
            {
                "name": "Brown",
                "confidence": 0.88
            },
            {
                "name": "Green",
                "confidence": 0.02
            },
            {
                "name": "Grey",
                "confidence": 0.09
            }
        ],
        "smile": 0.6,
        "age": 23.5
    },
    "bug_probability": 0.01
}