{
    "image": "generated.photos_v3_0538890.jpg",
    "faceLandmarks": {
        "mouth": [
            {
                "x": 408,
                "y": 728
            },
            {
                "x": 448,
                "y": 712
            },
            {
                "x": 488,
                "y": 704
            },
            {
                "x": 512,
                "y": 704
            },
            {
                "x": 536,
                "y": 704
            },
            {
                "x": 568,
                "y": 712
            },
            {
                "x": 616,
                "y": 728
            },
            {
                "x": 576,
                "y": 760
            },
            {
                "x": 536,
                "y": 768
            },
            {
                "x": 512,
                "y": 768
            },
            {
                "x": 488,
                "y": 768
            },
            {
                "x": 448,
                "y": 752
            },
            {
                "x": 424,
                "y": 728
            },
            {
                "x": 480,
                "y": 728
            },
            {
                "x": 512,
                "y": 736
            },
            {
                "x": 536,
                "y": 728
            },
            {
                "x": 600,
                "y": 736
            },
            {
                "x": 536,
                "y": 736
            },
            {
                "x": 512,
                "y": 736
            },
            {
                "x": 488,
                "y": 728
            }
        ],
        "right_eyebrow": [
            {
                "x": 272,
                "y": 424
            },
            {
                "x": 312,
                "y": 392
            },
            {
                "x": 360,
                "y": 384
            },
            {
                "x": 408,
                "y": 392
            },
            {
                "x": 464,
                "y": 408
            }
        ],
        "left_eyebrow": [
            {
                "x": 552,
                "y": 408
            },
            {
                "x": 600,
                "y": 392
            },
            {
                "x": 656,
                "y": 384
            },
            {
                "x": 704,
                "y": 392
            },
            {
                "x": 744,
                "y": 424
            }
        ],
        "right_eye": [
            {
                "x": 336,
                "y": 480
            },
            {
                "x": 368,
                "y": 464
            },
            {
                "x": 408,
                "y": 464
            },
            {
                "x": 440,
                "y": 496
            },
            {
                "x": 400,
                "y": 504
            },
            {
                "x": 368,
                "y": 496
            }
        ],
        "left_eye": [
            {
                "x": 576,
                "y": 496
            },
            {
                "x": 608,
                "y": 464
            },
            {
                "x": 648,
                "y": 464
            },
            {
                "x": 680,
                "y": 480
            },
            {
                "x": 648,
                "y": 496
            },
            {
                "x": 608,
                "y": 496
            }
        ],
        "nose": [
            {
                "x": 512,
                "y": 480
            },
            {
                "x": 512,
                "y": 520
            },
            {
                "x": 512,
                "y": 560
            },
            {
                "x": 512,
                "y": 608
            },
            {
                "x": 456,
                "y": 640
            },
            {
                "x": 488,
                "y": 648
            },
            {
                "x": 512,
                "y": 656
            },
            {
                "x": 536,
                "y": 648
            }
        ],
        "jaw": [
            {
                "x": 216,
                "y": 472
            },
            {
                "x": 224,
                "y": 544
            },
            {
                "x": 240,
                "y": 616
            },
            {
                "x": 248,
                "y": 688
            },
            {
                "x": 272,
                "y": 752
            },
            {
                "x": 320,
                "y": 808
            },
            {
                "x": 384,
                "y": 848
            },
            {
                "x": 448,
                "y": 888
            },
            {
                "x": 512,
                "y": 896
            },
            {
                "x": 584,
                "y": 888
            },
            {
                "x": 648,
                "y": 856
            },
            {
                "x": 704,
                "y": 816
            },
            {
                "x": 752,
                "y": 760
            },
            {
                "x": 768,
                "y": 688
            },
            {
                "x": 784,
                "y": 616
            },
            {
                "x": 792,
                "y": 544
            },
            {
                "x": 800,
                "y": 472
            }
        ]
    },
    "faceAttributes": {
        "headPose": {
            "pitch": -1.35,
            "roll": 0.13,
            "yaw": -0.23
        },
        "gender": {
            "male": 0.6,
            "female": 0.4
        },
        "makeup": {
            "eyeMakeup": 0.38,
            "lipMakeup": 0.2
        },
        "emotion": {
            "anger": 0.0,
            "contempt": 0.03,
            "disgust": 0.02,
            "fear": 0.0,
            "happiness": 0.46,
            "neutral": 0.43,
            "sadness": 0.05,
            "surprise": 0.02
        },
        "facialHair": {
            "moustache": 0.01,
            "beard": 0.0,
            "sideburns": 0.0
        },
        "hair": {
            "hairColor": [
                {
                    "name": "brown",
                    "confidence": 0.88
                },
                {
                    "name": "black",
                    "confidence": 0.67
                },
                {
                    "name": "blond",
                    "confidence": 0.35
                },
                {
                    "name": "red",
                    "confidence": 0.21
                },
                {
                    "name": "gray",
                    "confidence": 0.25
                },
                {
                    "name": "other",
                    "confidence": 0.19
                }
            ],
            "hairLength": [
                {
                    "name": "Long",
                    "confidence": 0.0
                },
                {
                    "name": "Medium",
                    "confidence": 0.63
                },
                {
                    "name": "Short",
                    "confidence": 0.6
                }
            ],
            "bald": 0.04
        },
        "occlusion": {
            "foreheadOccluded": 0.01,
            "eyeOccluded": 0.0,
            "mouthOccluded": 0.0
        },
        "ethnicity": [
            {
                "name": "asian",
                "confidence": 0.56
            },
            {
                "name": "black",
                "confidence": 0.0
            },
            {
                "name": "latino",
                "confidence": 0.14
            },
            {
                "name": "white",
                "confidence": 0.29
            }
        ],
        "eye_color": [
            {
                "name": "Blue",
                "confidence": 0.01
            },
            {
                "name": "Brown",
                "confidence": 0.95
            },
            {
                "name": "Green",
                "confidence": 0.01
            },
            {
                "name": "Grey",
                "confidence": 0.07
            }
        ],
        "smile": 0.46,
        "age": 10.58
    },
    "bug_probability": 0.04
}