{
    "image": "generated.photos_v3_0054904.jpg",
    "faceLandmarks": {
        "mouth": [
            {
                "x": 392,
                "y": 736
            },
            {
                "x": 440,
                "y": 720
            },
            {
                "x": 480,
                "y": 712
            },
            {
                "x": 512,
                "y": 712
            },
            {
                "x": 544,
                "y": 704
            },
            {
                "x": 584,
                "y": 720
            },
            {
                "x": 624,
                "y": 736
            },
            {
                "x": 584,
                "y": 776
            },
            {
                "x": 544,
                "y": 800
            },
            {
                "x": 512,
                "y": 800
            },
            {
                "x": 480,
                "y": 800
            },
            {
                "x": 440,
                "y": 776
            },
            {
                "x": 416,
                "y": 744
            },
            {
                "x": 480,
                "y": 736
            },
            {
                "x": 512,
                "y": 744
            },
            {
                "x": 544,
                "y": 736
            },
            {
                "x": 600,
                "y": 744
            },
            {
                "x": 544,
                "y": 752
            },
            {
                "x": 512,
                "y": 752
            },
            {
                "x": 480,
                "y": 752
            }
        ],
        "right_eyebrow": [
            {
                "x": 280,
                "y": 432
            },
            {
                "x": 320,
                "y": 400
            },
            {
                "x": 368,
                "y": 392
            },
            {
                "x": 416,
                "y": 400
            },
            {
                "x": 464,
                "y": 424
            }
        ],
        "left_eyebrow": [
            {
                "x": 560,
                "y": 424
            },
            {
                "x": 600,
                "y": 400
            },
            {
                "x": 648,
                "y": 392
            },
            {
                "x": 696,
                "y": 400
            },
            {
                "x": 728,
                "y": 432
            }
        ],
        "right_eye": [
            {
                "x": 336,
                "y": 488
            },
            {
                "x": 368,
                "y": 464
            },
            {
                "x": 400,
                "y": 472
            },
            {
                "x": 440,
                "y": 496
            },
            {
                "x": 400,
                "y": 496
            },
            {
                "x": 368,
                "y": 496
            }
        ],
        "left_eye": [
            {
                "x": 584,
                "y": 496
            },
            {
                "x": 608,
                "y": 464
            },
            {
                "x": 648,
                "y": 464
            },
            {
                "x": 680,
                "y": 488
            },
            {
                "x": 648,
                "y": 496
            },
            {
                "x": 616,
                "y": 496
            }
        ],
        "nose": [
            {
                "x": 512,
                "y": 472
            },
            {
                "x": 512,
                "y": 528
            },
            {
                "x": 512,
                "y": 576
            },
            {
                "x": 512,
                "y": 632
            },
            {
                "x": 456,
                "y": 656
            },
            {
                "x": 480,
                "y": 664
            },
            {
                "x": 512,
                "y": 672
            },
            {
                "x": 544,
                "y": 664
            }
        ],
        "jaw": [
            {
                "x": 216,
                "y": 480
            },
            {
                "x": 224,
                "y": 560
            },
            {
                "x": 232,
                "y": 632
            },
            {
                "x": 248,
                "y": 704
            },
            {
                "x": 272,
                "y": 768
            },
            {
                "x": 312,
                "y": 824
            },
            {
                "x": 368,
                "y": 872
            },
            {
                "x": 432,
                "y": 912
            },
            {
                "x": 504,
                "y": 920
            },
            {
                "x": 576,
                "y": 912
            },
            {
                "x": 632,
                "y": 872
            },
            {
                "x": 688,
                "y": 824
            },
            {
                "x": 728,
                "y": 768
            },
            {
                "x": 744,
                "y": 704
            },
            {
                "x": 760,
                "y": 632
            },
            {
                "x": 768,
                "y": 560
            },
            {
                "x": 776,
                "y": 488
            }
        ]
    },
    "faceAttributes": {
        "headPose": {
            "pitch": -1.93,
            "roll": 0.24,
            "yaw": 2.17
        },
        "gender": {
            "male": 0.14,
            "female": 0.86
        },
        "makeup": {
            "eyeMakeup": 0.78,
            "lipMakeup": 0.68
        },
        "emotion": {
            "anger": -0.0,
            "contempt": 0.03,
            "disgust": 0.02,
            "fear": 0.0,
            "happiness": 0.74,
            "neutral": 0.16,
            "sadness": 0.04,
            "surprise": 0.01
        },
        "facialHair": {
            "moustache": -0.01,
            "beard": -0.01,
            "sideburns": -0.01
        },
        "hair": {
            "hairColor": [
                {
                    "name": "brown",
                    "confidence": 0.9
                },
                {
                    "name": "black",
                    "confidence": 0.78
                },
                {
                    "name": "blond",
                    "confidence": 0.21
                },
                {
                    "name": "red",
                    "confidence": 0.17
                },
                {
                    "name": "gray",
                    "confidence": 0.3
                },
                {
                    "name": "other",
                    "confidence": 0.21
                }
            ],
            "hairLength": [
                {
                    "name": "Long",
                    "confidence": 0.05
                },
                {
                    "name": "Medium",
                    "confidence": 0.77
                },
                {
                    "name": "Short",
                    "confidence": 0.02
                }
            ],
            "bald": 0.15
        },
        "occlusion": {
            "foreheadOccluded": 0.0,
            "eyeOccluded": -0.0,
            "mouthOccluded": -0.0
        },
        "ethnicity": [
            {
                "name": "asian",
                "confidence": 0.2
            },
            {
                "name": "black",
                "confidence": 0.01
            },
            {
                "name": "latino",
                "confidence": 0.68
            },
            {
                "name": "white",
                "confidence": 0.12
            }
        ],
        "eye_color": [
            {
                "name": "Blue",
                "confidence": 0.05
            },
            {
                "name": "Brown",
                "confidence": 0.79
            },
            {
                "name": "Green",
                "confidence": 0.01
            },
            {
                "name": "Grey",
                "confidence": 0.12
            }
        ],
        "smile": 0.74,
        "age": 31.03
    },
    "bug_probability": 0.0
}