{
    "image": "generated.photos_v3_0688947.jpg",
    "faceLandmarks": {
        "mouth": [
            {
                "x": 384,
                "y": 736
            },
            {
                "x": 424,
                "y": 712
            },
            {
                "x": 464,
                "y": 704
            },
            {
                "x": 496,
                "y": 704
            },
            {
                "x": 528,
                "y": 696
            },
            {
                "x": 576,
                "y": 712
            },
            {
                "x": 624,
                "y": 736
            },
            {
                "x": 576,
                "y": 776
            },
            {
                "x": 536,
                "y": 800
            },
            {
                "x": 496,
                "y": 808
            },
            {
                "x": 464,
                "y": 800
            },
            {
                "x": 424,
                "y": 776
            },
            {
                "x": 408,
                "y": 744
            },
            {
                "x": 464,
                "y": 736
            },
            {
                "x": 496,
                "y": 736
            },
            {
                "x": 528,
                "y": 728
            },
            {
                "x": 600,
                "y": 736
            },
            {
                "x": 528,
                "y": 752
            },
            {
                "x": 496,
                "y": 752
            },
            {
                "x": 464,
                "y": 752
            }
        ],
        "right_eyebrow": [
            {
                "x": 288,
                "y": 424
            },
            {
                "x": 320,
                "y": 392
            },
            {
                "x": 360,
                "y": 384
            },
            {
                "x": 408,
                "y": 392
            },
            {
                "x": 448,
                "y": 408
            }
        ],
        "left_eyebrow": [
            {
                "x": 544,
                "y": 408
            },
            {
                "x": 592,
                "y": 392
            },
            {
                "x": 640,
                "y": 384
            },
            {
                "x": 688,
                "y": 392
            },
            {
                "x": 736,
                "y": 416
            }
        ],
        "right_eye": [
            {
                "x": 336,
                "y": 480
            },
            {
                "x": 360,
                "y": 464
            },
            {
                "x": 400,
                "y": 472
            },
            {
                "x": 432,
                "y": 488
            },
            {
                "x": 400,
                "y": 504
            },
            {
                "x": 360,
                "y": 504
            }
        ],
        "left_eye": [
            {
                "x": 576,
                "y": 488
            },
            {
                "x": 608,
                "y": 472
            },
            {
                "x": 648,
                "y": 464
            },
            {
                "x": 680,
                "y": 480
            },
            {
                "x": 648,
                "y": 496
            },
            {
                "x": 608,
                "y": 496
            }
        ],
        "nose": [
            {
                "x": 496,
                "y": 472
            },
            {
                "x": 496,
                "y": 520
            },
            {
                "x": 488,
                "y": 568
            },
            {
                "x": 488,
                "y": 616
            },
            {
                "x": 432,
                "y": 648
            },
            {
                "x": 464,
                "y": 656
            },
            {
                "x": 496,
                "y": 664
            },
            {
                "x": 528,
                "y": 656
            }
        ],
        "jaw": [
            {
                "x": 248,
                "y": 480
            },
            {
                "x": 248,
                "y": 544
            },
            {
                "x": 256,
                "y": 616
            },
            {
                "x": 264,
                "y": 688
            },
            {
                "x": 288,
                "y": 760
            },
            {
                "x": 320,
                "y": 816
            },
            {
                "x": 368,
                "y": 872
            },
            {
                "x": 424,
                "y": 920
            },
            {
                "x": 504,
                "y": 936
            },
            {
                "x": 584,
                "y": 928
            },
            {
                "x": 648,
                "y": 888
            },
            {
                "x": 712,
                "y": 840
            },
            {
                "x": 760,
                "y": 776
            },
            {
                "x": 792,
                "y": 704
            },
            {
                "x": 808,
                "y": 632
            },
            {
                "x": 816,
                "y": 552
            },
            {
                "x": 816,
                "y": 472
            }
        ]
    },
    "faceAttributes": {
        "headPose": {
            "pitch": -2.05,
            "roll": 0.01,
            "yaw": -7.48
        },
        "gender": {
            "male": 0.77,
            "female": 0.23
        },
        "makeup": {
            "eyeMakeup": 0.32,
            "lipMakeup": 0.27
        },
        "emotion": {
            "anger": 0.01,
            "contempt": 0.02,
            "disgust": 0.02,
            "fear": 0.0,
            "happiness": 0.73,
            "neutral": 0.21,
            "sadness": 0.02,
            "surprise": -0.01
        },
        "facialHair": {
            "moustache": 0.12,
            "beard": 0.12,
            "sideburns": 0.08
        },
        "hair": {
            "hairColor": [
                {
                    "name": "brown",
                    "confidence": 0.88
                },
                {
                    "name": "black",
                    "confidence": 0.85
                },
                {
                    "name": "blond",
                    "confidence": 0.19
                },
                {
                    "name": "red",
                    "confidence": 0.13
                },
                {
                    "name": "gray",
                    "confidence": 0.34
                },
                {
                    "name": "other",
                    "confidence": 0.25
                }
            ],
            "hairLength": [
                {
                    "name": "Long",
                    "confidence": 0.01
                },
                {
                    "name": "Medium",
                    "confidence": 0.02
                },
                {
                    "name": "Short",
                    "confidence": 1.0
                }
            ],
            "bald": 0.17
        },
        "occlusion": {
            "foreheadOccluded": -0.0,
            "eyeOccluded": -0.0,
            "mouthOccluded": -0.0
        },
        "ethnicity": [
            {
                "name": "asian",
                "confidence": 0.1
            },
            {
                "name": "black",
                "confidence": 0.04
            },
            {
                "name": "latino",
                "confidence": 0.76
            },
            {
                "name": "white",
                "confidence": 0.1
            }
        ],
        "eye_color": [
            {
                "name": "Blue",
                "confidence": 0.03
            },
            {
                "name": "Brown",
                "confidence": 0.88
            },
            {
                "name": "Green",
                "confidence": 0.05
            },
            {
                "name": "Grey",
                "confidence": 0.07
            }
        ],
        "smile": 0.73,
        "age": 28.7
    },
    "bug_probability": 0.01
}