{
    "image": "generated.photos_v3_0065346.jpg",
    "faceLandmarks": {
        "mouth": [
            {
                "x": 392,
                "y": 720
            },
            {
                "x": 424,
                "y": 704
            },
            {
                "x": 464,
                "y": 696
            },
            {
                "x": 496,
                "y": 696
            },
            {
                "x": 528,
                "y": 696
            },
            {
                "x": 584,
                "y": 704
            },
            {
                "x": 632,
                "y": 720
            },
            {
                "x": 584,
                "y": 776
            },
            {
                "x": 536,
                "y": 800
            },
            {
                "x": 496,
                "y": 800
            },
            {
                "x": 464,
                "y": 800
            },
            {
                "x": 424,
                "y": 776
            },
            {
                "x": 408,
                "y": 720
            },
            {
                "x": 464,
                "y": 720
            },
            {
                "x": 496,
                "y": 728
            },
            {
                "x": 528,
                "y": 720
            },
            {
                "x": 616,
                "y": 728
            },
            {
                "x": 536,
                "y": 760
            },
            {
                "x": 496,
                "y": 760
            },
            {
                "x": 464,
                "y": 760
            }
        ],
        "right_eyebrow": [
            {
                "x": 288,
                "y": 424
            },
            {
                "x": 320,
                "y": 392
            },
            {
                "x": 368,
                "y": 392
            },
            {
                "x": 408,
                "y": 408
            },
            {
                "x": 456,
                "y": 424
            }
        ],
        "left_eyebrow": [
            {
                "x": 544,
                "y": 424
            },
            {
                "x": 592,
                "y": 400
            },
            {
                "x": 648,
                "y": 392
            },
            {
                "x": 704,
                "y": 400
            },
            {
                "x": 744,
                "y": 432
            }
        ],
        "right_eye": [
            {
                "x": 336,
                "y": 480
            },
            {
                "x": 368,
                "y": 464
            },
            {
                "x": 408,
                "y": 464
            },
            {
                "x": 440,
                "y": 496
            },
            {
                "x": 400,
                "y": 504
            },
            {
                "x": 368,
                "y": 496
            }
        ],
        "left_eye": [
            {
                "x": 576,
                "y": 504
            },
            {
                "x": 608,
                "y": 472
            },
            {
                "x": 648,
                "y": 464
            },
            {
                "x": 680,
                "y": 488
            },
            {
                "x": 648,
                "y": 504
            },
            {
                "x": 616,
                "y": 504
            }
        ],
        "nose": [
            {
                "x": 496,
                "y": 480
            },
            {
                "x": 496,
                "y": 528
            },
            {
                "x": 488,
                "y": 576
            },
            {
                "x": 488,
                "y": 624
            },
            {
                "x": 440,
                "y": 648
            },
            {
                "x": 464,
                "y": 656
            },
            {
                "x": 488,
                "y": 672
            },
            {
                "x": 520,
                "y": 656
            }
        ],
        "jaw": [
            {
                "x": 272,
                "y": 488
            },
            {
                "x": 272,
                "y": 552
            },
            {
                "x": 272,
                "y": 616
            },
            {
                "x": 280,
                "y": 680
            },
            {
                "x": 304,
                "y": 744
            },
            {
                "x": 336,
                "y": 800
            },
            {
                "x": 376,
                "y": 856
            },
            {
                "x": 432,
                "y": 896
            },
            {
                "x": 496,
                "y": 920
            },
            {
                "x": 568,
                "y": 912
            },
            {
                "x": 648,
                "y": 880
            },
            {
                "x": 712,
                "y": 840
            },
            {
                "x": 760,
                "y": 776
            },
            {
                "x": 792,
                "y": 712
            },
            {
                "x": 800,
                "y": 632
            },
            {
                "x": 816,
                "y": 560
            },
            {
                "x": 816,
                "y": 480
            }
        ]
    },
    "faceAttributes": {
        "headPose": {
            "pitch": -4.53,
            "roll": 0.62,
            "yaw": -9.64
        },
        "gender": {
            "male": -0.06,
            "female": 1.06
        },
        "makeup": {
            "eyeMakeup": 0.95,
            "lipMakeup": 0.89
        },
        "emotion": {
            "anger": 0.0,
            "contempt": 0.02,
            "disgust": 0.02,
            "fear": 0.0,
            "happiness": 0.96,
            "neutral": -0.04,
            "sadness": 0.03,
            "surprise": 0.0
        },
        "facialHair": {
            "moustache": -0.02,
            "beard": -0.02,
            "sideburns": -0.01
        },
        "hair": {
            "hairColor": [
                {
                    "name": "brown",
                    "confidence": 0.98
                },
                {
                    "name": "black",
                    "confidence": 0.79
                },
                {
                    "name": "blond",
                    "confidence": 0.17
                },
                {
                    "name": "red",
                    "confidence": 0.24
                },
                {
                    "name": "gray",
                    "confidence": 0.21
                },
                {
                    "name": "other",
                    "confidence": 0.19
                }
            ],
            "hairLength": [
                {
                    "name": "Long",
                    "confidence": 0.9
                },
                {
                    "name": "Medium",
                    "confidence": 0.08
                },
                {
                    "name": "Short",
                    "confidence": 0.0
                }
            ],
            "bald": 0.1
        },
        "occlusion": {
            "foreheadOccluded": -0.01,
            "eyeOccluded": -0.0,
            "mouthOccluded": -0.0
        },
        "ethnicity": [
            {
                "name": "asian",
                "confidence": 0.11
            },
            {
                "name": "black",
                "confidence": 0.01
            },
            {
                "name": "latino",
                "confidence": 0.77
            },
            {
                "name": "white",
                "confidence": 0.12
            }
        ],
        "eye_color": [
            {
                "name": "Blue",
                "confidence": 0.0
            },
            {
                "name": "Brown",
                "confidence": 0.94
            },
            {
                "name": "Green",
                "confidence": 0.03
            },
            {
                "name": "Grey",
                "confidence": 0.03
            }
        ],
        "smile": 0.96,
        "age": 28.56
    },
    "bug_probability": 0.05
}